mkdocs_redoc_tag/__init__.py
mkdocs_redoc_tag/plugin.py
mkdocs_redoc_tag/redoc/LICENCE
mkdocs_redoc_tag/redoc/redoc.html
mkdocs_redoc_tag/redoc/javascripts/redark.js
mkdocs_redoc_tag/redoc/javascripts/redoc.standalone.js
mkdocs_redoc_tag/redoc/stylesheets/redark.css
mkdocs_redoc_tag-0.2.0.dist-info/METADATA
mkdocs_redoc_tag-0.2.0.dist-info/WHEEL
mkdocs_redoc_tag-0.2.0.dist-info/entry_points.txt
mkdocs_redoc_tag-0.2.0.dist-info/licenses/LICENSE
mkdocs_redoc_tag-0.2.0.dist-info/RECORD
