Metadata-Version: 2.4
Name: mkdocs-redoc-tag
Version: 0.2.0
Summary: A MkDocs plugin supports for add Redoc in page.
Project-URL: Homepage, https://blueswen.github.io/mkdocs-redoc-tag/
Project-URL: Source, https://github.com/blueswen/mkdocs-redoc-tag
Project-URL: Issues, https://github.com/blueswen/mkdocs-redoc-tag/issues
Project-URL: History, https://github.com/blueswen/mkdocs-redoc-tag/blob/main/CHANGELOG
Author-email: Blueswen <blueswen.tw@gmail.com>
License-Expression: MIT
License-File: LICENSE
Keywords: mkdocs,openapi,plugin,redoc
Classifier: Development Status :: 5 - Production/Stable
Classifier: Environment :: Console
Classifier: Environment :: Web Environment
Classifier: Intended Audience :: Developers
Classifier: License :: OSI Approved :: MIT License
Classifier: Operating System :: OS Independent
Classifier: Programming Language :: Python
Classifier: Programming Language :: Python :: 3
Classifier: Programming Language :: Python :: 3 :: Only
Classifier: Programming Language :: Python :: 3.8
Classifier: Programming Language :: Python :: 3.9
Classifier: Programming Language :: Python :: 3.10
Classifier: Programming Language :: Python :: 3.11
Classifier: Programming Language :: Python :: 3.12
Classifier: Topic :: Documentation
Classifier: Topic :: Text Processing
Requires-Python: >=3.8
Requires-Dist: beautifulsoup4>=4.13.3
